sh_junit_xml/__init__.py
sh_junit_xml/__main__.py
tests/__init__.py
tests/test_main.py
sh_junit_xml-1.0.0.dist-info/LICENSE
sh_junit_xml-1.0.0.dist-info/METADATA
sh_junit_xml-1.0.0.dist-info/WHEEL
sh_junit_xml-1.0.0.dist-info/entry_points.txt
sh_junit_xml-1.0.0.dist-info/top_level.txt
sh_junit_xml-1.0.0.dist-info/RECORD
