Metadata-Version: 2.1
Name: sh-junit-xml
Version: 1.0.0
Summary: A tool for generating junit output from a shell
Home-page: https://github.com/dandedrick/python-sh-junit-xml
Author: Dan Dedrick
Author-email: dan.dedrick@gmail.com
License: UNKNOWN
Platform: UNKNOWN
Classifier: License :: OSI Approved :: MIT License
Classifier: Operating System :: POSIX :: Linux
Classifier: Topic :: Utilities
Classifier: Programming Language :: Python :: 3
Requires-Python: >=3
License-File: LICENSE
Requires-Dist: junit-xml
